jupyterlab_indent_guides/__init__.py
jupyterlab_indent_guides/_version.py
jupyterlab_indent_guides-0.1.0.data/data/share/jupyter/labextensions/jupyterlab-indent-guides/package.json
jupyterlab_indent_guides-0.1.0.data/data/share/jupyter/labextensions/jupyterlab-indent-guides/static/568.5c22e584d4ce87865336.js
jupyterlab_indent_guides-0.1.0.data/data/share/jupyter/labextensions/jupyterlab-indent-guides/static/722.677deb4452682d2fd06c.js
jupyterlab_indent_guides-0.1.0.data/data/share/jupyter/labextensions/jupyterlab-indent-guides/static/747.dc18ed7a4c05a68678d6.js
jupyterlab_indent_guides-0.1.0.data/data/share/jupyter/labextensions/jupyterlab-indent-guides/static/remoteEntry.21946eee73703e66fa5a.js
jupyterlab_indent_guides-0.1.0.data/data/share/jupyter/labextensions/jupyterlab-indent-guides/static/style.js
jupyterlab_indent_guides-0.1.0.data/data/share/jupyter/labextensions/jupyterlab-indent-guides/static/third-party-licenses.json
jupyterlab_indent_guides-0.1.0.data/data/share/jupyter/labextensions/jupyterlab-indent-guides/install.json
jupyterlab_indent_guides-0.1.0.dist-info/METADATA
jupyterlab_indent_guides-0.1.0.dist-info/WHEEL
jupyterlab_indent_guides-0.1.0.dist-info/licenses/LICENSE
jupyterlab_indent_guides-0.1.0.dist-info/RECORD
