Metadata-Version: 2.1
Name: jupyterlab-indent-guides
Version: 0.1.0
Summary: Indentation guides for JupyterLab
Project-URL: Homepage, https://github.com/firai/jupyterlab-indent-guides
Project-URL: Bug Tracker, https://github.com/firai/jupyterlab-indent-guides/issues
Project-URL: Repository, https://github.com/firai/jupyterlab-indent-guides.git
Author-email: firai <firai.admin@gmail.com>
License: BSD 3-Clause License
License-File: LICENSE
Classifier: Framework :: Jupyter
Classifier: Framework :: Jupyter :: JupyterLab
Classifier: Framework :: Jupyter :: JupyterLab :: 4
Classifier: Framework :: Jupyter :: JupyterLab :: Extensions
Classifier: Framework :: Jupyter :: JupyterLab :: Extensions :: Prebuilt
Classifier: License :: OSI Approved :: BSD License
Classifier: Programming Language :: Python
Classifier: Programming Language :: Python :: 3
Classifier: Programming Language :: Python :: 3.8
Classifier: Programming Language :: Python :: 3.9
Classifier: Programming Language :: Python :: 3.10
Classifier: Programming Language :: Python :: 3.11
Requires-Python: >=3.8
